synap/__init__.py
synap/__init__.pyi
synap/_synap.cpython-310-aarch64-linux-gnu.so
synap/py.typed
synap/postprocessor/__init__.py
synap/postprocessor/__init__.pyi
synap/preprocessor/__init__.py
synap/preprocessor/__init__.pyi
synap/types/__init__.py
synap/types/__init__.pyi
synap_python-0.9.0.dist-info/LICENSE
synap_python-0.9.0.dist-info/METADATA
synap_python-0.9.0.dist-info/WHEEL
synap_python-0.9.0.dist-info/entry_points.txt
synap_python-0.9.0.dist-info/RECORD
