Metadata-Version: 2.1
Name: synap-python
Version: 0.9.0
Summary: Python bindings for SyNAP
Author-Email: Sauryadeep Pal <sauryadeep.pal@synaptics.com>
License:                                  Apache License
Requires-Python: >=3.10
Requires-Dist: numpy
